quickspider/__init__.py
quickspider/bin/__init__.py
quickspider/core/Node.py
quickspider/core/__init__.py
quickspider/core/builder.py
quickspider/core/controller.py
quickspider/core/custom.py
quickspider/core/error.py
quickspider/core/leafpool.py
quickspider/core/nodes.py
quickspider/core/utils.py
quickspider/custom/__init__.py
quickspider/custom/__pycache__/__init__.cpython-39.pyc
quickspider/custom/xmuLoginNode/__init__.py
quickspider/custom/xmuLoginNode/encrypt.py
quickspider/custom/xmuLoginNode/xmuLoginNode.py
quickspider/custom/xmuWebvpnNode/__init__.py
quickspider/custom/xmuWebvpnNode/aes-js.js
quickspider/custom/xmuWebvpnNode/portal.js
quickspider/custom/xmuWebvpnNode/xmuWebvpnNode.py
quickspider/template/__init__.py
quickspider/template/default.toml
quickspider/template/sheet.toml
quickspider/test/__init__.py
quickspider/test/test_nodes.py
quickspider-0.1.2.10.data/scripts/quickspidercommand
quickspider-0.1.2.10.dist-info/LICENSE
quickspider-0.1.2.10.dist-info/METADATA
quickspider-0.1.2.10.dist-info/WHEEL
quickspider-0.1.2.10.dist-info/top_level.txt
quickspider-0.1.2.10.dist-info/RECORD
