Metadata-Version: 2.1
Name: quickspider
Version: 0.1.2.10
Summary: help you build a small spider quickly.
Home-page: https://github.com/tiwe0/quickspider.git
Author: Ivory
Author-email: 1070642565@qq.com
License: UNKNOWN
Platform: UNKNOWN
License-File: LICENSE
